scrapy_llm/__init__.py
scrapy_llm/config.py
scrapy_llm/handler.py
scrapy_llm/types.py
scrapy_llm/utils.py
scrapy_llm-0.1.19.dist-info/LICENSE
scrapy_llm-0.1.19.dist-info/METADATA
scrapy_llm-0.1.19.dist-info/WHEEL
scrapy_llm-0.1.19.dist-info/top_level.txt
scrapy_llm-0.1.19.dist-info/RECORD
