Metadata-Version: 2.1
Name: scrapy-llm
Version: 0.1.19
Summary: LLM integration for Scrapy
Author-email: blacksuan19 <py@blacksuan19.dev>
Classifier: Programming Language :: Python
Classifier: Programming Language :: Python :: 3
Requires-Python: >=3.10
License-File: LICENSE
Requires-Dist: scrapy
Requires-Dist: html2text
Requires-Dist: instructor
Requires-Dist: litellm
Requires-Dist: pandas
Requires-Dist: pydantic
Provides-Extra: dev
Requires-Dist: black; extra == "dev"
Requires-Dist: bumpver; extra == "dev"
Requires-Dist: pip-tools; extra == "dev"
Requires-Dist: wheel; extra == "dev"
